ruffini/__init__.py
ruffini/fpolynomials.py
ruffini/monomials.py
ruffini/polynomials.py
ruffini/variables.py
ruffini-1.3.dist-info/METADATA
ruffini-1.3.dist-info/WHEEL
ruffini-1.3.dist-info/top_level.txt
ruffini-1.3.dist-info/RECORD
