Metadata-Version: 2.1
Name: ruffini
Version: 1.3
Summary: Monomials, Polynomials and lot more!
Home-page: https://github.com/gianluparri03/ruffini
Author: Gianluca Parri
Author-email: gianlucaparri03@gmail.com
License: MIT
Platform: UNKNOWN
